<mxfile host="app.diagrams.net" agent="Mozilla/5.0 (Windows NT 10.0; Win64; x64) AppleWebKit/537.36 (KHTML, like Gecko) Chrome/136.0.0.0 YaBrowser/25.6.0.0 Safari/537.36" version="26.1.1">
  <diagram name="Autopark Klassid" id="0">
    <mxGraphModel dx="1386" dy="805" grid="1" gridSize="10" guides="1" tooltips="1" connect="1" arrows="1" fold="1" page="1" pageScale="1" pageWidth="850" pageHeight="1100" math="0" shadow="0">
      <root>
        <mxCell id="0" />
        <mxCell id="1" parent="0" />
        <mxCell id="auto" value="Auto&lt;div&gt;&lt;br&gt;&lt;div&gt;Id&lt;/div&gt;&lt;div&gt;Tootja&lt;/div&gt;&lt;div&gt;&lt;span style=&quot;background-color: transparent; color: light-dark(rgb(0, 0, 0), rgb(255, 255, 255));&quot;&gt;Mudel&lt;/span&gt;&lt;/div&gt;&lt;div&gt;&lt;span style=&quot;background-color: transparent; color: light-dark(rgb(0, 0, 0), rgb(255, 255, 255));&quot;&gt;Numbrimärk&lt;/span&gt;&lt;/div&gt;&lt;/div&gt;" style="rounded=1;whiteSpace=wrap;html=1;fillColor=#d5e8d4;strokeColor=#82b366;" parent="1" vertex="1">
          <mxGeometry x="40" y="40" width="220" height="120" as="geometry" />
        </mxCell>
        <mxCell id="operatsioon" value="Operatsioon&lt;div&gt;&lt;br&gt;&lt;div&gt;Id&lt;/div&gt;&lt;div&gt;&lt;span style=&quot;background-color: transparent; color: light-dark(rgb(0, 0, 0), rgb(255, 255, 255));&quot;&gt;AutoId&lt;/span&gt;&lt;/div&gt;&lt;div&gt;TüüpId&lt;/div&gt;&lt;div&gt;TöötajaId&lt;/div&gt;&lt;div&gt;Kuupäev&lt;/div&gt;&lt;div&gt;Staatus&lt;/div&gt;&lt;div&gt;Maksumus&lt;/div&gt;&lt;/div&gt;" style="rounded=1;whiteSpace=wrap;html=1;fillColor=#dae8fc;strokeColor=#6c8ebf;" parent="1" vertex="1">
          <mxGeometry x="320" y="40" width="320" height="160" as="geometry" />
        </mxCell>
        <mxCell id="tyyp" value="Operatsiooni&lt;span style=&quot;background-color: transparent; color: light-dark(rgb(0, 0, 0), rgb(255, 255, 255));&quot;&gt;Tüüp&lt;/span&gt;&lt;div&gt;&lt;span style=&quot;background-color: transparent; color: light-dark(rgb(0, 0, 0), rgb(255, 255, 255));&quot;&gt;&lt;br&gt;&lt;/span&gt;&lt;/div&gt;&lt;div&gt;&lt;span style=&quot;background-color: transparent; color: light-dark(rgb(0, 0, 0), rgb(255, 255, 255));&quot;&gt;Id&lt;/span&gt;&lt;/div&gt;&lt;div&gt;&lt;span style=&quot;background-color: transparent; color: light-dark(rgb(0, 0, 0), rgb(255, 255, 255));&quot;&gt;Nimi&lt;/span&gt;&lt;/div&gt;&lt;div&gt;&lt;span style=&quot;background-color: transparent; color: light-dark(rgb(0, 0, 0), rgb(255, 255, 255));&quot;&gt;Kirjeldus&lt;/span&gt;&lt;/div&gt;" style="rounded=1;whiteSpace=wrap;html=1;fillColor=#fff2cc;strokeColor=#d6b656;" parent="1" vertex="1">
          <mxGeometry x="680" y="40" width="240" height="120" as="geometry" />
        </mxCell>
        <mxCell id="tootaja" value="Töötaja&lt;div&gt;&lt;br&gt;&lt;div&gt;Id&lt;/div&gt;&lt;div&gt;Nimi&lt;/div&gt;&lt;div&gt;Email&lt;/div&gt;&lt;div&gt;Roll&lt;/div&gt;&lt;/div&gt;" style="rounded=1;whiteSpace=wrap;html=1;fillColor=#f8cecc;strokeColor=#b85450;" parent="1" vertex="1">
          <mxGeometry x="320" y="240" width="320" height="120" as="geometry" />
        </mxCell>
        <mxCell id="edge_auto_oper" style="edgeStyle=orthogonalEdgeStyle;rounded=0;orthogonalLoop=1;jettySize=auto;html=1;" parent="1" source="auto" target="operatsioon" edge="1">
          <mxGeometry relative="1" as="geometry" />
        </mxCell>
        <mxCell id="edge_oper_tyyp" style="edgeStyle=orthogonalEdgeStyle;rounded=0;orthogonalLoop=1;jettySize=auto;html=1;" parent="1" source="operatsioon" target="tyyp" edge="1">
          <mxGeometry relative="1" as="geometry" />
        </mxCell>
        <mxCell id="edge_oper_to" style="edgeStyle=orthogonalEdgeStyle;rounded=0;orthogonalLoop=1;jettySize=auto;html=1;" parent="1" source="operatsioon" target="tootaja" edge="1">
          <mxGeometry relative="1" as="geometry" />
        </mxCell>
      </root>
    </mxGraphModel>
  </diagram>
</mxfile>
